{
  "demo/animate": {
    "js": "/assets/static/demo/animate-51466b8b.js",
    "css": "/assets/static/demo/animate-80d94d19.css"
  },
  "": {
    "json": "/manifest.json",
    "ttf": "/6f0a76321d30f3c8120915e57f7bd77e.ttf"
  },
  "demo/hello": {
    "js": "/assets/static/demo/hello-2e5fe2ba.js",
    "css": "/assets/static/demo/hello-0d60ea71.css"
  },
  "demo/hlj": {
    "js": "/assets/static/demo/hlj-acdd2fea.js",
    "css": "/assets/static/demo/hlj-0d60ea71.css"
  },
  "guess": {
    "js": "/assets/static/guess-e7d78a96.js",
    "css": "/assets/static/guess-0d60ea71.css"
  },
  "cms": {
    "js": "/assets/static/cms-1a8d5740.js",
    "css": "/assets/static/cms-0d60ea71.css"
  },
  "bear": {
    "js": "/assets/static/bear-ffffd45c.js",
    "css": "/assets/static/bear-61a5cf08.css"
  }
}